[
  {
    "id": 1,
    "day": "sunday",
    "workoutName": "pushup",
    "sets": "42",
    "reps": "54"
  },
  {
    "id": 2,
    "day": "sunday",
    "workoutName": "bench press",
    "sets": "52",
    "reps": "12"
  },
  {
    "id": 3,
    "day": "sunday",
    "workoutName": "situps",
    "sets": "46",
    "reps": "36"
  },
  {
    "id": 4,
    "day": "sunday",
    "workoutName": "rest",
    "sets": "68",
    "reps": "45"
  },
  {
    "id": 5,
    "day": "sunday",
    "workoutName": "jumping jacks",
    "sets": "56",
    "reps": "87"
  },
  {
    "id": 6,
    "day": "monday",
    "workoutName": "pushup",
    "sets": "68",
    "reps": "95"
  },
  {
    "id": 7,
    "day": "monday",
    "workoutName": "bench press",
    "sets": "45",
    "reps": "86"
  },
  {
    "id": 8,
    "day": "monday",
    "workoutName": "situps",
    "sets": "25",
    "reps": "16"
  },
  {
    "id": 9,
    "day": "monday",
    "workoutName": "rest",
    "sets": "97",
    "reps": "13"
  },
  {
    "id": 10,
    "day": "monday",
    "workoutName": "jumping jacks",
    "sets": "97",
    "reps": "65"
  },
  {
    "id": 11,
    "day": "tuesday",
    "workoutName": "pushup",
    "sets": "98",
    "reps": "12"
  },
  {
    "id": 12,
    "day": "tuesday",
    "workoutName": "bench press",
    "sets": "16",
    "reps": "56"
  },
  {
    "id": 13,
    "day": "tuesday",
    "workoutName": "situps",
    "sets": "26",
    "reps": "28"
  },
  {
    "id": 14,
    "day": "tuesday",
    "workoutName": "rest",
    "sets": "92",
    "reps": "57"
  },
  {
    "id": 15,
    "day": "tuesday",
    "workoutName": "jumping jacks",
    "sets": "19",
    "reps": "10"
  },
  {
    "id": 16,
    "day": "wednesday",
    "workoutName": "pushup",
    "sets": "49",
    "reps": "63"
  },
  {
    "id": 17,
    "day": "wednesday",
    "workoutName": "bench press",
    "sets": "15",
    "reps": "48"
  },
  {
    "id": 18,
    "day": "wednesday",
    "workoutName": "situps",
    "sets": "17",
    "reps": "49"
  },
  {
    "id": 19,
    "day": "wednesday",
    "workoutName": "rest",
    "sets": "98",
    "reps": "48"
  },
  {
    "id": 20,
    "day": "wednesday",
    "workoutName": "jumping jacks",
    "sets": "18",
    "reps": "29"
  },
  {
    "id": 21,
    "day": "thursday",
    "workoutName": "pushup",
    "sets": "48",
    "reps": "32"
  },
  {
    "id": 22,
    "day": "thursday",
    "workoutName": "bench press",
    "sets": "51",
    "reps": "96"
  },
  {
    "id": 23,
    "day": "thursday",
    "workoutName": "situps",
    "sets": "36",
    "reps": "41"
  },
  {
    "id": 24,
    "day": "thursday",
    "workoutName": "rest",
    "sets": "22",
    "reps": "43"
  },
  {
    "id": 25,
    "day": "thursday",
    "workoutName": "jumping jacks",
    "sets": "33",
    "reps": "11"
  },
  {
    "id": 26,
    "day": "friday",
    "workoutName": "pushup",
    "sets": "16",
    "reps": "56"
  },
  {
    "id": 27,
    "day": "friday",
    "workoutName": "bench press",
    "sets": "49",
    "reps": "95"
  },
  {
    "id": 28,
    "day": "friday",
    "workoutName": "situps",
    "sets": "84",
    "reps": "56"
  },
  {
    "id": 29,
    "day": "friday",
    "workoutName": "rest",
    "sets": "92",
    "reps": "49"
  },
  {
    "id": 30,
    "day": "friday",
    "workoutName": "jumping jacks",
    "sets": "35",
    "reps": "29"
  },
  {
    "id": 31,
    "day": "saturday",
    "workoutName": "pushup",
    "sets": "19",
    "reps": "35"
  },
  {
    "id": 32,
    "day": "saturday",
    "workoutName": "bench press",
    "sets": "62",
    "reps": "19"
  },
  {
    "id": 33,
    "day": "saturday",
    "workoutName": "situps",
    "sets": "44",
    "reps": "21"
  },
  {
    "id": 34,
    "day": "saturday",
    "workoutName": "rest",
    "sets": "19",
    "reps": "16"
  },
  {
    "id": 35,
    "day": "saturday",
    "workoutName": "jumping jacks",
    "sets": "53",
    "reps": "45"
  }
]
